rootify/__init__.py
rootify/rootify.py
rootify-0.2.dist-info/METADATA
rootify-0.2.dist-info/WHEEL
rootify-0.2.dist-info/top_level.txt
rootify-0.2.dist-info/RECORD
