Metadata-Version: 2.1
Name: rootify
Version: 0.2
Summary: A simple package to change the working directory to the project root based on a marker.
Home-page: https://github.com/jimmys-code/rootify
Author: Jimmys-Code
Author-email: jazcogames@gmail.com
Classifier: Programming Language :: Python :: 3
Classifier: License :: OSI Approved :: MIT License
Classifier: Operating System :: OS Independent
Requires-Python: >=3.6
